netcdf_scm/__init__.py
netcdf_scm/_version.py
netcdf_scm/cli.py
netcdf_scm/cli_parallel.py
netcdf_scm/cli_utils.py
netcdf_scm/crunching.py
netcdf_scm/definitions.py
netcdf_scm/errors.py
netcdf_scm/io.py
netcdf_scm/iris_cube_wrappers.py
netcdf_scm/misc_readers.py
netcdf_scm/output.py
netcdf_scm/retractions.py
netcdf_scm/stitching.py
netcdf_scm/utils.py
netcdf_scm/wranglers.py
netcdf_scm/wrangling.py
netcdf_scm/citing/__init__.py
netcdf_scm/citing/cmip5.py
netcdf_scm/citing/cmip5_climate-model_scenario_citations.csv
netcdf_scm/citing/cmip6.py
netcdf_scm/mat4py/__init__.py
netcdf_scm/mat4py/loadmat.py
netcdf_scm/mat4py/savemat.py
netcdf_scm/normalisation/__init__.py
netcdf_scm/normalisation/after_branch_time_mean.py
netcdf_scm/normalisation/base.py
netcdf_scm/normalisation/running_mean.py
netcdf_scm/normalisation/running_mean_dedrift.py
netcdf_scm/weights/__init__.py
netcdf_scm/weights/default_land_ocean_weights.nc
netcdf_scm-2.1.1.dist-info/LICENSE
netcdf_scm-2.1.1.dist-info/METADATA
netcdf_scm-2.1.1.dist-info/WHEEL
netcdf_scm-2.1.1.dist-info/entry_points.txt
netcdf_scm-2.1.1.dist-info/top_level.txt
netcdf_scm-2.1.1.dist-info/RECORD
