Metadata-Version: 2.1
Name: netcdf-scm
Version: 2.1.1
Summary: Processing netCDF files for use with simple climate models
Home-page: https://github.com/znicholls/netcdf-scm
Author: Zebedee Nicholls
Author-email: zebedee.nicholls@climate-energy-college.org
License: 3-Clause BSD License
Project-URL: Bug Reports, https://github.com/znicholls/netcdf-scm/issues
Project-URL: Documentation, https://openscm.readthedocs.io/en/latest
Project-URL: Source, https://github.com/znicholls/netcdf-scm
Keywords: netcdf,netCDF,python,climate,atmosphere,simple climate model,reduced complexity climate model,data processing
Platform: UNKNOWN
Classifier: Development Status :: 4 - Beta
Classifier: License :: OSI Approved :: BSD License
Classifier: Intended Audience :: Developers
Classifier: Operating System :: OS Independent
Classifier: Programming Language :: Python :: 3.7
Requires-Dist: cf-units (>=3.0)
Requires-Dist: cftime (>=1.4)
Requires-Dist: click
Requires-Dist: numpy
Requires-Dist: python-dateutil
Requires-Dist: pymagicc (>=2.0.0)
Requires-Dist: scmdata (>=0.7)
Requires-Dist: scipy
Requires-Dist: tqdm
Requires-Dist: xarray (>=0.18)
Provides-Extra: ar6regions
Requires-Dist: regionmask (>=0.6) ; extra == 'ar6regions'
Provides-Extra: deploy
Requires-Dist: twine (>=1.11.0) ; extra == 'deploy'
Requires-Dist: setuptools (>=38.6.0) ; extra == 'deploy'
Requires-Dist: wheel (>=0.31.0) ; extra == 'deploy'
Provides-Extra: dev
Requires-Dist: bandit ; extra == 'dev'
Requires-Dist: beautifulsoup4 ; extra == 'dev'
Requires-Dist: black (==19.10b0) ; extra == 'dev'
Requires-Dist: black-nb ; extra == 'dev'
Requires-Dist: flake8 ; extra == 'dev'
Requires-Dist: isort ; extra == 'dev'
Requires-Dist: mypy ; extra == 'dev'
Requires-Dist: nbdime ; extra == 'dev'
Requires-Dist: pydocstyle ; extra == 'dev'
Requires-Dist: pylint (>=2.4.0) ; extra == 'dev'
Requires-Dist: regionmask (>=0.6) ; extra == 'dev'
Requires-Dist: twine (>=1.11.0) ; extra == 'dev'
Requires-Dist: setuptools (>=38.6.0) ; extra == 'dev'
Requires-Dist: wheel (>=0.31.0) ; extra == 'dev'
Requires-Dist: nbsphinx ; extra == 'dev'
Requires-Dist: sphinx (<2.1,>=1.4) ; extra == 'dev'
Requires-Dist: sphinx-rtd-theme ; extra == 'dev'
Requires-Dist: sphinx-click ; extra == 'dev'
Requires-Dist: sphinx-copybutton ; extra == 'dev'
Requires-Dist: ipywidgets ; extra == 'dev'
Requires-Dist: notebook ; extra == 'dev'
Requires-Dist: expectexception ; extra == 'dev'
Requires-Dist: seaborn ; extra == 'dev'
Requires-Dist: codecov ; extra == 'dev'
Requires-Dist: nbval ; extra == 'dev'
Requires-Dist: pytest (<5.0,>=4.0) ; extra == 'dev'
Requires-Dist: pytest-benchmark ; extra == 'dev'
Requires-Dist: pytest-cov ; extra == 'dev'
Requires-Dist: pytest-console-scripts ; extra == 'dev'
Requires-Dist: pytest-xdist ; extra == 'dev'
Provides-Extra: docs
Requires-Dist: nbsphinx ; extra == 'docs'
Requires-Dist: sphinx (<2.1,>=1.4) ; extra == 'docs'
Requires-Dist: sphinx-rtd-theme ; extra == 'docs'
Requires-Dist: sphinx-click ; extra == 'docs'
Requires-Dist: sphinx-copybutton ; extra == 'docs'
Provides-Extra: notebooks
Requires-Dist: ipywidgets ; extra == 'notebooks'
Requires-Dist: notebook ; extra == 'notebooks'
Requires-Dist: expectexception ; extra == 'notebooks'
Requires-Dist: seaborn ; extra == 'notebooks'
Provides-Extra: tests
Requires-Dist: codecov ; extra == 'tests'
Requires-Dist: nbval ; extra == 'tests'
Requires-Dist: pytest (<5.0,>=4.0) ; extra == 'tests'
Requires-Dist: pytest-benchmark ; extra == 'tests'
Requires-Dist: pytest-cov ; extra == 'tests'
Requires-Dist: pytest-console-scripts ; extra == 'tests'
Requires-Dist: pytest-xdist ; extra == 'tests'
